Qubits/Qubits.py
Qubits/__init__.py
Kala_Qubits-0.1.0.dist-info/METADATA
Kala_Qubits-0.1.0.dist-info/WHEEL
Kala_Qubits-0.1.0.dist-info/top_level.txt
Kala_Qubits-0.1.0.dist-info/RECORD
