Metadata-Version: 2.1
Name: Kala_Qubits
Version: 0.1.0
Summary: A lightweight quantum circuit simulator with PyTorch backend
Home-page: https://github.com/Kalasaikamesh944/Qubits
Author: N V R K SAI KAMESH YADAVALLI
Author-email: saikamesh.y@gmail.com
Classifier: Programming Language :: Python :: 3
Classifier: License :: OSI Approved :: MIT License
Classifier: Operating System :: OS Independent
Requires-Python: >=3.8
Requires-Dist: numpy>=1.20.0
Requires-Dist: torch>=1.10.0
